SalesforceEinsteinAnalytics/SFDC_EA.py
SalesforceEinsteinAnalytics/__init__.py
SalesforceEinsteinAnalytics-0.0.1.dist-info/LICENSE
SalesforceEinsteinAnalytics-0.0.1.dist-info/METADATA
SalesforceEinsteinAnalytics-0.0.1.dist-info/WHEEL
SalesforceEinsteinAnalytics-0.0.1.dist-info/top_level.txt
SalesforceEinsteinAnalytics-0.0.1.dist-info/RECORD
