Metadata-Version: 2.1
Name: SalesforceEinsteinAnalytics
Version: 0.0.1
Summary: Python package for working with the Einstein Analytics API
Home-page: https://github.com/ahilgenkamp/SalesforceEinsteinAnalytics
Author: Adam Hilgenkamp
Author-email: ahilgie@gmail.com
License: UNKNOWN
Platform: UNKNOWN
Classifier: Programming Language :: Python :: 3
Classifier: License :: OSI Approved :: MIT License
Classifier: Operating System :: OS Independent
Requires-Python: >=3.6
